{"task_id": "db6b3ba8-51aa-469b-9eaf-43f1ee6459aa", "tool": "fpocket", "queue": "cpu", "status": "completed", "created_at": "2026-03-22T15:54:49.063891", "started_at": "2026-03-22T15:54:49.091315", "completed_at": null, "result": {"pockets": [{"pocket_id": 1, "score": 2.334, "druggability_score": 0.999, "number_of_alpha_spheres": 927.0, "total_sasa": 1158.725, "polar_sasa": 582.527, "apolar_sasa": 576.198, "volume": 4921.479, "mean_local_hydrophobic_density": 47.396, "mean_alpha_sphere_radius": 3.604, "mean_alp_sph_solvent_access": 0.447, "apolar_alpha_sphere_proportion": 0.457, "hydrophobicity_score": 38.782, "volume_score": 4.331, "polarity_score": 56.0, "charge_score": 7.0, "proportion_of_polar_atoms": 35.731, "alpha_sphere_density": 19.179, "cent_of_mass_-_alpha_sphere_max_dist": 52.868, "flexibility": 0.202, "x_bary_(sph)": -43.432, "y_bary_(sph)": -28.704, "z_bary_(sph)": 22.937}, {"pocket_id": 2, "score": 0.274, "druggability_score": 0.035, "number_of_alpha_spheres": 195.0, "total_sasa": 366.695, "polar_sasa": 222.987, "apolar_sasa": 143.708, "volume": 1526.516, "mean_local_hydrophobic_density": 21.676, "mean_alpha_sphere_radius": 3.633, "mean_alp_sph_solvent_access": 0.51, "apolar_alpha_sphere_proportion": 0.349, "hydrophobicity_score": 18.676, "volume_score": 4.029, "polarity_score": 20.0, "charge_score": -1.0, "proportion_of_polar_atoms": 40.0, "alpha_sphere_density": 11.515, "cent_of_mass_-_alpha_sphere_max_dist": 27.576, "flexibility": 0.113, "x_bary_(sph)": -46.891, "y_bary_(sph)": -24.23, "z_bary_(sph)": 41.939}, {"pocket_id": 3, "score": 0.105, "druggability_score": 0.005, "number_of_alpha_spheres": 15.0, "total_sasa": 33.677, "polar_sasa": 1.071, "apolar_sasa": 32.606, "volume": 119.928, "mean_local_hydrophobic_density": 14.0, "mean_alpha_sphere_radius": 3.231, "mean_alp_sph_solvent_access": 0.422, "apolar_alpha_sphere_proportion": 1.0, "hydrophobicity_score": 64.833, "volume_score": 5.0, "polarity_score": 1.0, "charge_score": 0.0, "proportion_of_polar_atoms": 20.0, "alpha_sphere_density": 2.958, "cent_of_mass_-_alpha_sphere_max_dist": 5.478, "flexibility": 0.03, "x_bary_(sph)": -46.659, "y_bary_(sph)": -36.274, "z_bary_(sph)": 55.103}, {"pocket_id": 4, "score": 0.09, "druggability_score": 0.003, "number_of_alpha_spheres": 25.0, "total_sasa": 58.133, "polar_sasa": 21.429, "apolar_sasa": 36.704, "volume": 202.645, "mean_local_hydrophobic_density": 8.909, "mean_alpha_sphere_radius": 3.495, "mean_alp_sph_solvent_access": 0.516, "apolar_alpha_sphere_proportion": 0.44, "hydrophobicity_score": 38.556, "volume_score": 4.0, "polarity_score": 4.0, "charge_score": 0.0, "proportion_of_polar_atoms": 42.857, "alpha_sphere_density": 3.765, "cent_of_mass_-_alpha_sphere_max_dist": 8.197, "flexibility": 0.114, "x_bary_(sph)": -31.299, "y_bary_(sph)": -27.548, "z_bary_(sph)": 52.89}, {"pocket_id": 5, "score": 0.066, "druggability_score": 0.001, "number_of_alpha_spheres": 16.0, "total_sasa": 9.275, "polar_sasa": 3.237, "apolar_sasa": 6.038, "volume": 62.822, "mean_local_hydrophobic_density": 4.0, "mean_alpha_sphere_radius": 3.298, "mean_alp_sph_solvent_access": 0.391, "apolar_alpha_sphere_proportion": 0.312, "hydrophobicity_score": 72.25, "volume_score": 4.625, "polarity_score": 0.0, "charge_score": 0.0, "proportion_of_polar_atoms": 30.769, "alpha_sphere_density": 1.467, "cent_of_mass_-_alpha_sphere_max_dist": 4.969, "flexibility": 0.057, "x_bary_(sph)": -30.468, "y_bary_(sph)": -28.455, "z_bary_(sph)": 37.048}, {"pocket_id": 6, "score": 0.031, "druggability_score": 0.001, "number_of_alpha_spheres": 20.0, "total_sasa": 59.709, "polar_sasa": 24.688, "apolar_sasa": 35.021, "volume": 215.583, "mean_local_hydrophobic_density": 5.0, "mean_alpha_sphere_radius": 3.467, "mean_alp_sph_solvent_access": 0.526, "apolar_alpha_sphere_proportion": 0.3, "hydrophobicity_score": 16.0, "volume_score": 4.286, "polarity_score": 4.0, "charge_score": 1.0, "proportion_of_polar_atoms": 44.444, "alpha_sphere_density": 3.228, "cent_of_mass_-_alpha_sphere_max_dist": 7.391, "flexibility": 0.423, "x_bary_(sph)": -49.902, "y_bary_(sph)": -39.334, "z_bary_(sph)": 2.776}, {"pocket_id": 7, "score": 0.021, "druggability_score": 0.232, "number_of_alpha_spheres": 42.0, "total_sasa": 125.194, "polar_sasa": 33.414, "apolar_sasa": 91.78, "volume": 436.373, "mean_local_hydrophobic_density": 28.471, "mean_alpha_sphere_radius": 3.588, "mean_alp_sph_solvent_access": 0.53, "apolar_alpha_sphere_proportion": 0.81, "hydrophobicity_score": 38.455, "volume_score": 4.364, "polarity_score": 6.0, "charge_score": 1.0, "proportion_of_polar_atoms": 27.273, "alpha_sphere_density": 5.647, "cent_of_mass_-_alpha_sphere_max_dist": 14.268, "flexibility": 0.591, "x_bary_(sph)": -51.321, "y_bary_(sph)": -27.146, "z_bary_(sph)": -6.012}, {"pocket_id": 8, "score": 0.017, "druggability_score": 0.0, "number_of_alpha_spheres": 17.0, "total_sasa": 65.8, "polar_sasa": 44.063, "apolar_sasa": 21.737, "volume": 212.819, "mean_local_hydrophobic_density": 0.0, "mean_alpha_sphere_radius": 3.56, "mean_alp_sph_solvent_access": 0.571, "apolar_alpha_sphere_proportion": 0.059, "hydrophobicity_score": -3.714, "volume_score": 3.286, "polarity_score": 6.0, "charge_score": 0.0, "proportion_of_polar_atoms": 64.706, "alpha_sphere_density": 3.372, "cent_of_mass_-_alpha_sphere_max_dist": 7.524, "flexibility": 0.371, "x_bary_(sph)": -63.149, "y_bary_(sph)": -37.971, "z_bary_(sph)": 11.047}, {"pocket_id": 9, "score": 0.011, "druggability_score": 0.0, "number_of_alpha_spheres": 19.0, "total_sasa": 39.544, "polar_sasa": 21.429, "apolar_sasa": 18.114, "volume": 133.005, "mean_local_hydrophobic_density": 1.0, "mean_alpha_sphere_radius": 3.601, "mean_alp_sph_solvent_access": 0.63, "apolar_alpha_sphere_proportion": 0.105, "hydrophobicity_score": 4.6, "volume_score": 3.4, "polarity_score": 2.0, "charge_score": -1.0, "proportion_of_polar_atoms": 53.333, "alpha_sphere_density": 2.173, "cent_of_mass_-_alpha_sphere_max_dist": 4.808, "flexibility": 0.446, "x_bary_(sph)": -37.118, "y_bary_(sph)": -16.323, "z_bary_(sph)": 0.942}, {"pocket_id": 10, "score": -0.016, "druggability_score": 0.002, "number_of_alpha_spheres": 32.0, "total_sasa": 120.032, "polar_sasa": 77.765, "apolar_sasa": 42.267, "volume": 420.513, "mean_local_hydrophobic_density": 4.0, "mean_alpha_sphere_radius": 3.656, "mean_alp_sph_solvent_access": 0.594, "apolar_alpha_sphere_proportion": 0.156, "hydrophobicity_score": -1.3, "volume_score": 4.0, "polarity_score": 7.0, "charge_score": 1.0, "proportion_of_polar_atoms": 46.429, "alpha_sphere_density": 5.15, "cent_of_mass_-_alpha_sphere_max_dist": 15.309, "flexibility": 0.396, "x_bary_(sph)": -60.146, "y_bary_(sph)": -26.841, "z_bary_(sph)": -0.118}], "output_dir": "/data/oih/outputs/cd36_tier3_v5_fpocket/fpocket", "num_pockets": 35}, "error": null, "progress": 100, "progress_msg": "Found 35 pocket(s).", "output_files": [], "updated_at": "2026-03-22T15:54:51.378000"}